{
  "display": {
    "icon": {
      "id": "datanessence:ecliptrum_ingot"
    },
    "title": {
      "translate": "advancements.datanessence.acquire_ecliptrum.title"
    },
    "description": {
      "translate": "advancements.datanessence.acquire_ecliptrum.description"
    },
    "hidden": true
  },
  "parent": "datanessence:progression/acquire_lunar_essence_shard",
  "criteria": {
    "has_ecliptrum": {
      "trigger": "minecraft:inventory_changed",
      "conditions": { "items": [ { "items": ["datanessence:ecliptrum_ingot" ] } ] }
    }
  }
}
